{
  "cookies": [
    {
      "name": "next-auth.csrf-token",
      "value": "4cba88a743bddace920f9ddd316731518733ec1d52cb2a59d0d2539e8535e831%7C30746dd8d1cf806a2c59dc48e469d662e1ef547c6737cb8fde26977a4d97eb83",
      "domain": "localhost",
      "path": "/",
      "expires": -1,
      "httpOnly": true,
      "secure": false,
      "sameSite": "Lax"
    },
    {
      "name": "next-auth.callback-url",
      "value": "http%3A%2F%2Flocalhost%3A3000%2Flist",
      "domain": "localhost",
      "path": "/",
      "expires": -1,
      "httpOnly": true,
      "secure": false,
      "sameSite": "Lax"
    },
    {
      "name": "next-auth.session-token",
      "value": "eyJhbGciOiJkaXIiLCJlbmMiOiJBMjU2R0NNIn0..ht-sF8ej10XXc831.4Wq0N6WAA8sNETjsBleTbjgH-SC07ClgZZLM1UB2Tlbq02ShcMM5LsDXvqYp5sb46xbloy_ZcTeMwEJXcxVe0FsS0ri1H8__U8QhMgrcVTP-xA6oQzFuD7nEKjmNK4grHjXXHWQDH-uutIBuJCxDGNz6WzXcZqsS00O6l9Ku2dNzjyi90b0XYL7dv4Vkck-Kg4pG.EcM8BHd2fX_sh0fFouDnDw",
      "domain": "localhost",
      "path": "/",
      "expires": 1749361691.037666,
      "httpOnly": true,
      "secure": false,
      "sameSite": "Lax"
    }
  ],
  "origins": [
    {
      "origin": "http://localhost:3000",
      "localStorage": [
        {
          "name": "nextauth.message",
          "value": "{\"event\":\"session\",\"data\":{\"trigger\":\"getSession\"},\"timestamp\":1746769691}"
        }
      ]
    }
  ]
}